zoho_mcp/__init__.py
zoho_mcp/auth_flow.py
zoho_mcp/errors.py
zoho_mcp/logging.py
zoho_mcp/server.py
zoho_mcp/transport.py
zoho_mcp/config/__init__.py
zoho_mcp/config/settings.py
zoho_mcp/models/__init__.py
zoho_mcp/models/base.py
zoho_mcp/models/contacts.py
zoho_mcp/models/expenses.py
zoho_mcp/models/invoices.py
zoho_mcp/models/items.py
zoho_mcp/models/sales.py
zoho_mcp/tools/__init__.py
zoho_mcp/tools/api.py
zoho_mcp/tools/contacts.py
zoho_mcp/tools/expenses.py
zoho_mcp/tools/invoices.py
zoho_mcp/tools/items.py
zoho_mcp/tools/sales.py
zoho_mcp-0.1.3.dist-info/METADATA
zoho_mcp-0.1.3.dist-info/WHEEL
zoho_mcp-0.1.3.dist-info/entry_points.txt
zoho_mcp-0.1.3.dist-info/licenses/LICENSE
zoho_mcp-0.1.3.dist-info/RECORD
