Metadata-Version: 2.4
Name: zoho-mcp
Version: 0.1.3
Summary: A Model Control Protocol (MCP) server that exposes tools for interacting with Zoho Books
Author: SkanderBS
License: MIT
License-File: LICENSE
Classifier: Development Status :: 4 - Beta
Classifier: Intended Audience :: Developers
Classifier: License :: OSI Approved :: MIT License
Classifier: Programming Language :: Python :: 3
Classifier: Programming Language :: Python :: 3.9
Classifier: Programming Language :: Python :: 3.10
Classifier: Programming Language :: Python :: 3.11
Requires-Python: >=3.10
Requires-Dist: asyncio>=3.4.3
Requires-Dist: click>=8.1.0
Requires-Dist: email-validator>=2.0.0
Requires-Dist: httpx>=0.25.0
Requires-Dist: mcp
Requires-Dist: pydantic>=2.4.0
Requires-Dist: python-dotenv>=1.0.0
Requires-Dist: structlog>=23.1.0
Provides-Extra: test
Requires-Dist: pytest-asyncio>=0.21.0; extra == 'test'
Requires-Dist: pytest-cov>=4.1.0; extra == 'test'
Requires-Dist: pytest-httpx>=0.25.0; extra == 'test'
Requires-Dist: pytest>=7.0.0; extra == 'test'
